parsehecssp/__init__.py
parsehecssp/volumeFrequency.py
parsehecssp/features/__init__.py
parsehecssp/features/feature.py
parsehecssp/features/header.py
parsehecssp/features/inputdata.py
parsehecssp/features/nDayResults.py
parsehecssp/features/utils.py
parsehecssp-0.0.1.dist-info/LICENSE
parsehecssp-0.0.1.dist-info/METADATA
parsehecssp-0.0.1.dist-info/WHEEL
parsehecssp-0.0.1.dist-info/top_level.txt
parsehecssp-0.0.1.dist-info/RECORD
