Metadata-Version: 2.1
Name: parsehecssp
Version: 0.0.1
Summary: Parse HEC-SSP report Files
Author: Daniel Hamill
Author-email: daniel.hamill@hey.com
License: MIT
Classifier: Development Status :: 4 - Beta
Classifier: Intended Audience :: Developers
Classifier: Intended Audience :: Science/Research
Classifier: License :: OSI Approved :: MIT License
Classifier: Operating System :: OS Independent
Classifier: Programming Language :: Python :: 3.7
Classifier: Programming Language :: Python :: 3.8
Classifier: Programming Language :: Python :: 3.9
Classifier: Topic :: Utilities
Classifier: Topic :: Scientific/Engineering :: GIS
License-File: LICENSE
